MANIFEST.in
README.md
setup.cfg
setup.py
csvloader/__init__.py
csvloader/csvload.py
csvloader/csvloaderData/data.csv
python_csvloader_dpp_example.egg-info/PKG-INFO
python_csvloader_dpp_example.egg-info/SOURCES.txt
python_csvloader_dpp_example.egg-info/dependency_links.txt
python_csvloader_dpp_example.egg-info/requires.txt
python_csvloader_dpp_example.egg-info/top_level.txt