Metadata-Version: 1.0
Name: python-csvloader-dpp-example
Version: 4.5
Summary: An example python package
Home-page: https://git.e-science.pl/rbaszak230509/81a_RBaszak_Package
Author: Rafal Baszak
Author-email: rbaszak230509@e-science.pl
License: MIT
Platform: UNKNOWN
